pylufic/__init__.py
pylufic/pylufic.py
pylufic-1.0.1.dist-info/LICENSE
pylufic-1.0.1.dist-info/METADATA
pylufic-1.0.1.dist-info/WHEEL
pylufic-1.0.1.dist-info/entry_points.txt
pylufic-1.0.1.dist-info/top_level.txt
pylufic-1.0.1.dist-info/RECORD
