Metadata-Version: 2.1
Name: pylufic
Version: 1.0.1
Summary: CLI client for lufi service
Home-page: https://framagit.org/setop/pylufic
Author: setop
Author-email: setop@zoocoop.com
License: UNKNOWN
Platform: UNKNOWN
Classifier: Programming Language :: Python :: 3
Classifier: License :: OSI Approved :: MIT License
Classifier: Operating System :: OS Independent
Classifier: Development Status :: 5 - Production/Stable
Classifier: Environment :: Console
Classifier: Intended Audience :: End Users/Desktop
Requires-Dist: baker
Requires-Dist: python-magic
Requires-Dist: sjcl
Requires-Dist: tqdm
Requires-Dist: websocket-client
